{
  "kategori": [
    {
      "nama": "KERESAHAN",
      "artikel": [
        {
          "judul": "About Humans",
          "url": "../artikel/keresahan/01/about-humans.html"
        },
        {
          "judul": "Fenomena Brain Root",
          "url": "../artikel/keresahan/01/Brain-root.html"
        },
        {
          "judul": "Hirarki Ilmu Pengetahua",
          "url": "../artikel/keresahan/01/Hirarki-ilmu-pengetahuan.html"
        }
      ]
    },
    {
      "nama": "SUMMARY BOOKS",
      "artikel": [
        {
          "judul": "Novel Insight About Humans #0",
          "url": "/artikel/summary-books/about"
        },
        {
          "judul": "Ringkasan Buku 'Atomic Habits'",
          "url": "/artikel/summary-books/atomic-habits/"
        },
        {
          "judul": "Ringkasan Buku 'Sapiens'",
          "url": "/artikel/summary-books/sapiens/"
        },
        {
          "judul": "Ringkasan Buku 'The Almanack of Naval Ravikant'",
          "url": "/artikel/summary-books/almanack-of-naval-ravikant/"
        }
      ]
    },
    {
      "nama": "SCIENCE",
      "artikel": [
        {
          "judul": "Memahami Konsep Lubang Hitam",
          "url": "/artikel/science/memahami-lubang-hitam/"
        },
        {
          "judul": "Penjelasan Sederhana tentang Entropi",
          "url": "/artikel/science/penjelasan-entropi/"
        }
      ]
    },
    {
      "nama": "HISTORY",
      "artikel": [
        {
          "judul": "Alasan Kebencian Nazi Pada Yahudi",
          "url": "../artikel/history/alasan-nazi-membenti-yahudi.html"
        },
        {
          "judul": "Revolusi Industri dan Dampaknya",
          "url": "/artikel/history/revolusi-industri/"
        }
      ]
    },
    {
      "nama": "PHILOSOPHY",
      "artikel": [
        {
          "judul": "Pengantar Filsafat Stoikisme",
          "url": "/artikel/philosophy/pengantar-stoikisme/"
        },
        {
          "judul": "Eksistensialisme: Kebebasan dan Tanggung Jawab",
          "url": "/artikel/philosophy/eksistensialisme-dan-kebebasan/"
        }
      ]
    }
  ]
}
